Artemisa/__init__.py
Artemisa/Extractor/__init__.py
Artemisa/Extractor/excel/__init__.py
Artemisa/Extractor/excel/excel.py
Artemisa/Extractor/pdf/__init__.py
Artemisa/Extractor/pdf/pdf.py
Artemisa/Extractor/pptx/__init__.py
Artemisa/Extractor/pptx/powerpoint.py
Artemisa/Extractor/word/__init__.py
Artemisa/Extractor/word/word.py
Artemisa/Indexer/__init__.py
Artemisa/Indexer/index.py
Artemisa/Indexer/search.py
Artemisa/Llm/__init__.py
Artemisa/Llm/deepresearcherlocal/__init__.py
Artemisa/Llm/deepresearcherlocal/prompts.py
Artemisa/Llm/deepresearcherlocal/researchlocal.py
Artemisa/Llm/deepresearcherlocal/search.py
Artemisa/Llm/deepresearcherlocal/state.py
Artemisa/Llm/deepresearcherlocal/utils.py
Artemisa/Llm/deepresearcheronline/__init__.py
Artemisa/Llm/deepresearcheronline/config.py
Artemisa/Llm/deepresearcheronline/deepresearcher.py
Artemisa/Llm/deepresearcheronline/prompts.py
Artemisa/Llm/deepresearcheronline/state.py
Artemisa/Llm/deepresearcheronline/utils.py
Artemisa/Llm/local/__init__.py
Artemisa/Llm/local/localollama.py
Artemisa/Llm/providers/__init__.py
Artemisa/Llm/providers/anthropic.py
Artemisa/Llm/providers/deep_seek_hf.py
Artemisa/Llm/providers/googleapi.py
Artemisa/Llm/providers/hf.py
Artemisa/Llm/providers/openai.py
artemisa-0.3.0.dist-info/METADATA
artemisa-0.3.0.dist-info/WHEEL
artemisa-0.3.0.dist-info/RECORD
