Metadata-Version: 2.4
Name: Artemisa
Version: 0.3.0
Summary: Sistema de extración de información de documentos
Author-email: "Rivera.ai/Fredy Rivera" <riveraaai200678@gmail.com>
Requires-Python: >=3.8
Requires-Dist: anthropic
Requires-Dist: google-genai
Requires-Dist: googlesearch-python
Requires-Dist: huggingface-hub
Requires-Dist: langchain
Requires-Dist: langgraph
Requires-Dist: ollama
Requires-Dist: openai
Requires-Dist: openpyxl
Requires-Dist: pandas
Requires-Dist: pydantic
Requires-Dist: pymupdf
Requires-Dist: python-docx
Requires-Dist: python-pptx
